omtx/__init__.py
omtx/client.py
omtx/exceptions.py
omtx/py.typed
omtx-0.4.2.dist-info/licenses/LICENSE
omtx-0.4.2.dist-info/METADATA
omtx-0.4.2.dist-info/WHEEL
omtx-0.4.2.dist-info/top_level.txt
omtx-0.4.2.dist-info/RECORD
