Metadata-Version: 2.4
Name: omtx
Version: 0.4.2
Summary: Python SDK for Om
Home-page: https://github.com/omtx/python-sdk
Author: Om
Author-email: Om <hello@omtx.ai>
License: MIT License
Project-URL: Homepage, https://github.com/omtx-ai/om-public
Project-URL: Issues, https://github.com/omtx-ai/om-public/issues
Classifier: Programming Language :: Python :: 3
Classifier: License :: OSI Approved :: MIT License
Classifier: Operating System :: OS Independent
Classifier: Typing :: Typed
Requires-Python: >=3.9
License-File: LICENSE
Requires-Dist: requests>=2.31.0
Requires-Dist: pandas>=1.5
Dynamic: author
Dynamic: home-page
Dynamic: license-file
Dynamic: requires-python
